ALifeStdDev/__init__.py
ALifeStdDev/ALifeStdDev/__init__.py
ALifeStdDev/phylogeny/__init__.py
ALifeStdDev/phylogeny/loader.py
ALifeStdDev/phylogeny/metrics.py
ALifeStdDev/phylogeny/utils.py
ALifeStdDev-0.3.3.dist-info/LICENSE
ALifeStdDev-0.3.3.dist-info/METADATA
ALifeStdDev-0.3.3.dist-info/WHEEL
ALifeStdDev-0.3.3.dist-info/top_level.txt
ALifeStdDev-0.3.3.dist-info/RECORD
