Metadata-Version: 2.1
Name: ALifeStdDev
Version: 0.3.3
Summary: Python development tools for working with standardized ALife data.
Home-page: https://github.com/alife-data-standards/alife-std-dev-python
Author: Emily Dolson, Alex Lalejini, Matthew Andres Moreno
Author-email: dolsonem@msu.edu, lalejini@msu.edu, morenoma@umich.edu
License: MIT
Keywords: artificial life
Platform: UNKNOWN
Classifier: Development Status :: 2 - Pre-Alpha
Classifier: Intended Audience :: Developers
Classifier: License :: OSI Approved :: MIT License
Classifier: Natural Language :: English
Classifier: Programming Language :: Python :: 3
Classifier: Programming Language :: Python :: 3.7
Classifier: Programming Language :: Python :: 3.8
Classifier: Programming Language :: Python :: 3.9
Classifier: Programming Language :: Python :: 3.10
Requires-Python: >=3.7
Requires-Dist: networkx
Requires-Dist: pandas
